{
  "featureTypes": {
    "gemeentehuizen": {
      "style": {
        "drawingMode": "Point",
        "fillColor": "#ffffff",
        "strokeColor": "#000088",
        "strokeWidth": 2,
        "stroke": true,
        "fillOpacity": 0.9,
        "opacity": 0.9,
        "iconWidth": 28,
        "iconHeight": 28,
        "nameLabel": "Name",
        "iconUri": "images/gemeentehuizen.png"
      },
      "propertyTypeKeys": "X;Y;X-nav;Y-nav;Bagvobid;Organisati;LOC_TYPE;LOC_NAAM;LOC_STRAAT;Huisnr;Postcode;Woonplaats;GEM;Regio;Website;Telefoon;BIJZONDERH"
    }
  },
  "propertyTypeData": {
    "X": {
      "title": "X",
      "type": "number",
      "description": ""
    },
    "Y": {
      "title": "Y",
      "type": "number",
      "description": ""
    },
    "X-nav": {
      "title": "X-nav",
      "type": "number",
      "description": ""
    },
    "Y-nav": {
      "title": "Y-nav",
      "type": "number",
      "description": ""
    },
    "Bagvobid": {
      "title": "Bagvobid",
      "type": "number",
      "description": ""
    },
    "Organisati": {
      "title": "Organisati",
      "type": "textarea",
      "description": ""
    },
    "LOC_TYPE": {
      "title": "Loc type",
      "type": "text",
      "description": ""
    },
    "LOC_NAAM": {
      "title": "Loc naam",
      "type": "textarea",
      "description": ""
    },
    "LOC_STRAAT": {
      "title": "Loc straat",
      "type": "textarea",
      "description": ""
    },
    "Huisnr": {
      "title": "Huisnr",
      "type": "number",
      "description": ""
    },
    "Postcode": {
      "title": "Postcode",
      "type": "text",
      "description": ""
    },
    "Woonplaats": {
      "title": "Woonplaats",
      "type": "text",
      "description": ""
    },
    "GEM": {
      "title": "Gem",
      "type": "text",
      "description": ""
    },
    "Regio": {
      "title": "Regio",
      "type": "number",
      "description": ""
    },
    "Website": {
      "title": "Website",
      "type": "bbcode",
      "description": "",
      "stringFormat": "[url=http://{0}]website[/url]"
    },
    "Telefoon": {
      "title": "Telefoon",
      "type": "text",
      "description": ""
    },
    "BIJZONDERH": {
      "title": "Bijzonderh",
      "type": "number",
      "description": ""
    }
  }
}